easy_literature/DBLP.py
easy_literature/GoogleScholar.py
easy_literature/Scholarly.py
easy_literature/__init__.py
easy_literature/arxiv.py
easy_literature/crossref.py
easy_literature/dblp_source.py
easy_literature/dlbp.py
easy_literature/downloads.py
easy_literature/easyliter.py
easy_literature/medbiorxiv.py
easy_literature/pdfs.py
easy_literature/utils.py
easyliter-1.0.5.dist-info/LICENSE
easyliter-1.0.5.dist-info/METADATA
easyliter-1.0.5.dist-info/WHEEL
easyliter-1.0.5.dist-info/entry_points.txt
easyliter-1.0.5.dist-info/top_level.txt
easyliter-1.0.5.dist-info/RECORD
