Metadata-Version: 2.1
Name: easyliter
Version: 1.0.5
Summary: EasyLiterature is a opensourced, Python-based command line tool for automatic literature management. Simply list the paper titles (or ids) you want to read in a markdown file and it will automatically collect and refine its information in the markdown file, download the pdf to your local machine, and link the pdf to your paper in the markdown file. You can forever keep your notes within the pdfs and mds on your local machine or cloud driver.
Home-page: https://github.com/Psycoy/EasyLiterature
Author: Oliver
Author-email: olivernova1998@gmail.com
License: AGPLv3
Keywords: title,bibtex,arxiv,doi,science,scientific-journals
Classifier: License :: OSI Approved :: GNU Affero General Public License v3 or later (AGPLv3+)
Classifier: Intended Audience :: Science/Research
Classifier: Programming Language :: Python :: 3
Classifier: Topic :: Text Processing :: Markup
License-File: LICENSE
Requires-Dist: beautifulsoup4 (>=4.11.1)
Requires-Dist: feedparser (>=6.0.10)
Requires-Dist: urllib3 (>=1.26.11)
Requires-Dist: requests (>=2.28.1)
Requires-Dist: tqdm (>=4.64.0)
Requires-Dist: Unidecode (>=1.3.4)
Requires-Dist: bibtexparser (==1.4.0)
Requires-Dist: pandas
Requires-Dist: scholarly
